managed_browser/__init__.py
managed_browser/managed_browser.py
managed_browser-0.2.0.dist-info/licenses/LICENSE
managed_browser-0.2.0.dist-info/METADATA
managed_browser-0.2.0.dist-info/WHEEL
managed_browser-0.2.0.dist-info/top_level.txt
managed_browser-0.2.0.dist-info/RECORD
