Metadata-Version: 2.4
Name: managed-browser
Version: 0.2.0
Summary: Allows seamless interplay between agentic browser-use and Playwright internals
Author-email: Amrit Baveja <abaveja313@gmail.com>
License: MIT License
Project-URL: Homepage, https://github.com/abaveja313/managed-browser
Project-URL: Repository, https://github.com/abaveja313/managed-browser
Keywords: playwright,browser,agent,automation,LLM
Classifier: Development Status :: 4 - Beta
Classifier: Intended Audience :: Developers
Classifier: License :: OSI Approved :: MIT License
Classifier: Programming Language :: Python :: 3
Classifier: Programming Language :: Python :: 3.11
Classifier: Programming Language :: Python :: 3.10
Classifier: Topic :: Software Development :: Libraries
Requires-Python: >=3.11
License-File: LICENSE
Requires-Dist: browser-use==0.2.2
Requires-Dist: fake-useragent>=2.2.0
Requires-Dist: langchain>=0.3.22
Dynamic: license-file
